vbmc/__init__.py
vbmc/_classes.py
vbmc/_kernel.py
vbmc/_score.py
vbmc/utilities.py
vbmc-0.0.0.dist-info/LICENSE
vbmc-0.0.0.dist-info/METADATA
vbmc-0.0.0.dist-info/WHEEL
vbmc-0.0.0.dist-info/top_level.txt
vbmc-0.0.0.dist-info/RECORD
