Metadata-Version: 2.1
Name: vbmc
Version: 0.0.0
Summary: CPU version of Voxel-based Monte Carlo simulation
Home-page: https://github.com/Kaname21Miura/vbmc.git
Author: Kaname Miura
Author-email: miukana21@gmail.com
License: MIT License
License-File: LICENSE
Requires-Dist: numpy
Requires-Dist: matplotlib
Requires-Dist: numba
